container_runner/__init__.py
container_runner/transformations.py
container_runner-0.4.0.dist-info/LICENSE
container_runner-0.4.0.dist-info/WHEEL
container_runner-0.4.0.dist-info/METADATA
container_runner-0.4.0.dist-info/RECORD
