Metadata-Version: 2.1
Name: container_runner
Version: 0.4.0
Summary: A template Python module
Home-page: https://github.com/IslasGECI/container_runner
Author: Ciencia de Datos • GECI
Author-email: ciencia.datos@islas.org.mx
Requires-Python: >=3.9
Classifier: License :: OSI Approved :: GNU General Public License v3 or later (GPLv3+)
